prettydiff/__init__.py
prettydiff/diff_obj.py
prettydiff/prettydiff.py
prettydiff/terminal.py
prettydiff-0.1.0.dist-info/LICENSE
prettydiff-0.1.0.dist-info/METADATA
prettydiff-0.1.0.dist-info/WHEEL
prettydiff-0.1.0.dist-info/top_level.txt
prettydiff-0.1.0.dist-info/RECORD
