Metadata-Version: 2.1
Name: prettydiff
Version: 0.1.0
Summary: Pretty JSON data diffs
Home-page: https://github.com/python273/prettydiff
Author: python273
Author-email: prettydiff@python273.pw
License: MIT
Download-URL: https://github.com/python273/prettydiff/archive/v0.1.0.zip
Platform: UNKNOWN
Classifier: License :: OSI Approved :: MIT License
Classifier: Operating System :: OS Independent
Classifier: Programming Language :: Python
Classifier: Programming Language :: Python :: 3
Classifier: Programming Language :: Python :: 3.6
Classifier: Programming Language :: Python :: 3.7
Classifier: Programming Language :: Python :: 3.8
Classifier: Programming Language :: Python :: 3.9
Requires-Python: >=3.6
Provides-Extra: terminal
Requires-Dist: colorama ; extra == 'terminal'
